jlhpy/__init__.py
jlhpy/version.py
jlhpy/utilities/__init__.py
jlhpy/utilities/generate_pack_sphere_packmol_template_context.py
jlhpy/utilities/analysis/__init__.py
jlhpy/utilities/analysis/count_components.py
jlhpy/utilities/analysis/forces.py
jlhpy/utilities/analysis/map_distances_and_frames.py
jlhpy/utilities/analysis/mpi_msd.py
jlhpy/utilities/analysis/mpi_rdf.py
jlhpy/utilities/analysis/msd.py
jlhpy/utilities/analysis/rdf.py
jlhpy/utilities/geometry/__init__.py
jlhpy/utilities/geometry/bounding_box.py
jlhpy/utilities/geometry/bounding_sphere.py
jlhpy/utilities/geometry/morphology.py
jlhpy/utilities/geometry/simulation_box.py
jlhpy/utilities/mpi/__init__.py
jlhpy/utilities/mpi/launcher.py
jlhpy/utilities/prep/__init__.py
jlhpy/utilities/prep/convert.py
jlhpy/utilities/prep/create_fcc_111.py
jlhpy/utilities/prep/merge.py
jlhpy/utilities/prep/random.py
jlhpy/utilities/prep/segids.py
jlhpy/utilities/prep/unwrap.py
jlhpy/utilities/templates/__init__.py
jlhpy/utilities/templates/cylindrical_packing.py
jlhpy/utilities/templates/flat_packing.py
jlhpy/utilities/templates/spherical_packing.py
jlhpy/utilities/vis/__init__.py
jlhpy/utilities/vis/plot_side_views_with_boxes.py
jlhpy/utilities/vis/plot_side_views_with_spheres.py
jlhpy/utilities/wf/__init__.py
jlhpy/utilities/wf/file_config.py
jlhpy/utilities/wf/grep.txt
jlhpy/utilities/wf/hpc_config.py
jlhpy/utilities/wf/mappings.py
jlhpy/utilities/wf/phys_config.py
jlhpy/utilities/wf/sub_wf_as_leaf_compact.txt
jlhpy/utilities/wf/sub_wf_as_root_compact.txt
jlhpy/utilities/wf/sub_wf_concept.txt
jlhpy/utilities/wf/sub_wf_independent_compact.txt
jlhpy/utilities/wf/utils.py
jlhpy/utilities/wf/workflow_generator.py
jlhpy/utilities/wf/building_blocks/__init__.py
jlhpy/utilities/wf/building_blocks/sub_wf_count_components.py
jlhpy/utilities/wf/building_blocks/sub_wf_gromacs_analysis.py
jlhpy/utilities/wf/building_blocks/sub_wf_gromacs_vis.py
jlhpy/utilities/wf/building_blocks/sub_wf_lammps_analysis.py
jlhpy-0.3.0.dist-info/licenses/LICENSE
jlhpy-0.3.0.dist-info/METADATA
jlhpy-0.3.0.dist-info/WHEEL
jlhpy-0.3.0.dist-info/top_level.txt
jlhpy-0.3.0.dist-info/RECORD
