Metadata-Version: 2.4
Name: jlhpy
Version: 0.3.0
Summary: Nanotribology of surfactants
Author-email: Johannes Hörmann <johannes.hoermann@imtek.uni-freiburg.de>
License: MIT
Project-URL: Homepage, https://github.com/jotelha/jlhphd
Requires-Python: >=3.6.5
License-File: LICENSE
Requires-Dist: fireworks>=1.9.5
Dynamic: license-file
